py_HighSierraMediaKeyEnabler-0.0.2-py3.8-nspkg.pth
scs/mediakeyenabler/__init__.py
scs/mediakeyenabler/__main__.py
scs/mediakeyenabler/tests/__init__.py
scs/mediakeyenabler/tests/test_mediakeyenabler.py
py_HighSierraMediaKeyEnabler-0.0.2.dist-info/LICENSE
py_HighSierraMediaKeyEnabler-0.0.2.dist-info/METADATA
py_HighSierraMediaKeyEnabler-0.0.2.dist-info/WHEEL
py_HighSierraMediaKeyEnabler-0.0.2.dist-info/entry_points.txt
py_HighSierraMediaKeyEnabler-0.0.2.dist-info/namespace_packages.txt
py_HighSierraMediaKeyEnabler-0.0.2.dist-info/top_level.txt
py_HighSierraMediaKeyEnabler-0.0.2.dist-info/zip-safe
py_HighSierraMediaKeyEnabler-0.0.2.dist-info/RECORD
