Metadata-Version: 2.1
Name: py-HighSierraMediaKeyEnabler
Version: 0.0.2
Summary: Python version of HighSierraMediaKeyEnabler
Home-page: https://github.com/jamadden/py-HighSierraMediaKeyEnabler
Author: Jason Madden
Author-email: jason@nextthought.com
License: Public Domain
Keywords: macOS media key
Platform: UNKNOWN
Classifier: Natural Language :: English
Classifier: Operating System :: MacOS :: MacOS X
Classifier: License :: Public Domain
Classifier: Programming Language :: Python :: 2.7
Classifier: Programming Language :: Python :: 3.7
Classifier: Programming Language :: Python :: 3.8
Classifier: Programming Language :: Python :: Implementation :: CPython
Requires-Python: >=2.7,!=3.0.*,!=3.1.*,!=3.2.*,!=3.3.*,!=3.4.*
Requires-Dist: setuptools
Requires-Dist: pyobjc
Provides-Extra: test
Requires-Dist: zope.testrunner ; extra == 'test'
Requires-Dist: mock ; (python_version == "2.7") and extra == 'test'
